<TestingKnowledges>
    <!--  data transfer instructions  -->
    <TK inst = "fadd">
        <Node name = "farith" weight="100"> </Node>
        <Node name = "normal" weight="0"> </Node>
    </TK>
    <TK inst = "faddp">
        <Node name = "farith" weight="100"> </Node>
        <Node name = "normal" weight="0"> </Node>
    </TK>
    <TK inst = "fiadd">
        <Node name = "farith" weight="100"> </Node>
        <Node name = "normal" weight="0"> </Node>
    </TK>
	<TK inst = "fld">
		<Node name = "farith" weight="100"> </Node>
        <Node name = "normal" weight="0"> </Node>
	</TK>
	<TK inst = "fxch">
		<Node name = "farith" weight="100"> </Node>
        <Node name = "normal" weight="0"> </Node>
	</TK>
	<TK inst = "fcmovb">
		<Node name = "farith" weight="100"> </Node>
        <Node name = "normal" weight="0"> </Node>
	</TK>
    <!-- user mode extended sate save/restore instructions -->
    <!-- TODO -->

    <!-- random number generator instructions -->
    <!-- TODO -->

    <!-- bmi1, bmi2 -->
    <!-- TODO -->

</TestingKnowledges>
